alregcode/__init__.py
AlRegCode-0.0.3.dist-info/LICENSE
AlRegCode-0.0.3.dist-info/METADATA
AlRegCode-0.0.3.dist-info/WHEEL
AlRegCode-0.0.3.dist-info/top_level.txt
AlRegCode-0.0.3.dist-info/RECORD
