Metadata-Version: 2.1
Name: AlRegCode
Version: 0.0.3
Summary: The Small Package For Generate Increment Registration Code
Home-page: https://alphacsoft.com
Author: M Nasrul Alawy
Author-email: alphacsoft@gmail.com
License: UNKNOWN
Platform: UNKNOWN
Classifier: Programming Language :: Python :: 3
Classifier: License :: OSI Approved :: MIT License
Classifier: Operating System :: OS Independent
